LICENSE
MANIFEST.in
README.rst
baas32.py
setup.cfg
setup.py
baas32.egg-info/PKG-INFO
baas32.egg-info/SOURCES.txt
baas32.egg-info/dependency_links.txt
baas32.egg-info/top_level.txt