Metadata-Version: 1.1
Name: baas32
Version: 0.3.1
Summary: An alternative Python implementation of Douglas Crockford's base32 encoding scheme
Home-page: https://github.com/klaplong/baas32.git
Author: Bas van den Heuvel
Author-email: vdheuvel.bas@gmail.com
License: BSD
Download-URL: https://pypi.python.org/pypi/baas32/
Platform: UNKNOWN
Classifier: Development Status :: 4 - Beta
Classifier: Intended Audience :: Developers
Classifier: License :: OSI Approved :: BSD License
Classifier: Operating System :: OS Independent
Classifier: Programming Language :: Python
Classifier: Programming Language :: Python :: 2
Classifier: Programming Language :: Python :: 2.6
Classifier: Programming Language :: Python :: 2.7
Classifier: Programming Language :: Python :: 3
Classifier: Programming Language :: Python :: 3.3
Classifier: Programming Language :: Python :: 3.4
Classifier: Topic :: Software Development :: Libraries :: Python Modules
Classifier: Topic :: Utilities
